vexy_pdf_werk/__init__.py
vexy_pdf_werk/__main__.py
vexy_pdf_werk/_version.py
vexy_pdf_werk/cli.py
vexy_pdf_werk/config.py
vexy_pdf_werk/py.typed
vexy_pdf_werk/vexy_pdf_werk.py
vexy_pdf_werk/core/__init__.py
vexy_pdf_werk/core/epub_creator.py
vexy_pdf_werk/core/markdown_converter.py
vexy_pdf_werk/core/metadata_extractor.py
vexy_pdf_werk/core/pdf_processor.py
vexy_pdf_werk/core/qdf_processor.py
vexy_pdf_werk/integrations/__init__.py
vexy_pdf_werk/integrations/ai_services.py
vexy_pdf_werk/utils/__init__.py
vexy_pdf_werk/utils/file_utils.py
vexy_pdf_werk/utils/slug_utils.py
vexy_pdf_werk/utils/validation.py
vexy_pdf_werk-1.1.9.dist-info/METADATA
vexy_pdf_werk-1.1.9.dist-info/WHEEL
vexy_pdf_werk-1.1.9.dist-info/entry_points.txt
vexy_pdf_werk-1.1.9.dist-info/licenses/LICENSE
vexy_pdf_werk-1.1.9.dist-info/RECORD
