Metadata-Version: 2.4
Name: vexy-pdf-werk
Version: 1.1.9
Project-URL: Documentation, https://github.com/vexyart/vexy-pdf-werk#readme
Project-URL: Issues, https://github.com/vexyart/vexy-pdf-werk/issues
Project-URL: Source, https://github.com/vexyart/vexy-pdf-werk
Author-email: Fontlab Ltd <opensource@vexy.art>
License: MIT
License-File: LICENSE
Classifier: Development Status :: 4 - Beta
Classifier: Intended Audience :: Developers
Classifier: License :: OSI Approved :: MIT License
Classifier: Operating System :: OS Independent
Classifier: Programming Language :: Python
Classifier: Programming Language :: Python :: 3.10
Classifier: Programming Language :: Python :: 3.11
Classifier: Programming Language :: Python :: 3.12
Classifier: Programming Language :: Python :: Implementation :: CPython
Classifier: Programming Language :: Python :: Implementation :: PyPy
Requires-Python: >=3.10
Requires-Dist: aiofiles>=24.1.0
Requires-Dist: aiohttp>=3.12.15
Requires-Dist: ebooklib>=0.19
Requires-Dist: fire>=0.7.1
Requires-Dist: loguru>=0.7.3
Requires-Dist: pathvalidate>=3.3.1
Requires-Dist: pikepdf>=9.11.0
Requires-Dist: platformdirs>=4.4.0
Requires-Dist: pydantic>=2.11.9
Requires-Dist: pypdf>=6.0.0
Requires-Dist: pyyaml>=6.0.2
Requires-Dist: reportlab>=4.4.3
Requires-Dist: requests>=2.32.5
Requires-Dist: rich>=14.1.0
Requires-Dist: toml>=0.10.2
Requires-Dist: unicode-slugify>=0.1.5
Provides-Extra: all
Provides-Extra: dev
Requires-Dist: absolufy-imports>=0.3.1; extra == 'dev'
Requires-Dist: isort>=6.0.1; extra == 'dev'
Requires-Dist: mypy>=1.15.0; extra == 'dev'
Requires-Dist: pre-commit>=4.1.0; extra == 'dev'
Requires-Dist: pyupgrade>=3.19.1; extra == 'dev'
Requires-Dist: ruff>=0.9.7; extra == 'dev'
Provides-Extra: docs
Requires-Dist: mkdocs-material>=9.5.0; extra == 'docs'
Requires-Dist: mkdocs>=1.6.0; extra == 'docs'
Provides-Extra: test
Requires-Dist: coverage[toml]>=7.6.12; extra == 'test'
Requires-Dist: pytest-asyncio>=0.25.3; extra == 'test'
Requires-Dist: pytest-benchmark[histogram]>=5.1.0; extra == 'test'
Requires-Dist: pytest-cov>=6.0.0; extra == 'test'
Requires-Dist: pytest-xdist>=3.6.1; extra == 'test'
Requires-Dist: pytest>=8.3.4; extra == 'test'
